README.md
setup.cfg
setup.py
Topsis_Kamal_102103259/Topsis_102103259.py
Topsis_Kamal_102103259/__init__.py
Topsis_Kamal_102103259/__main__.py
Topsis_Kamal_102103259.egg-info/PKG-INFO
Topsis_Kamal_102103259.egg-info/SOURCES.txt
Topsis_Kamal_102103259.egg-info/dependency_links.txt
Topsis_Kamal_102103259.egg-info/entry_points.txt
Topsis_Kamal_102103259.egg-info/requires.txt
Topsis_Kamal_102103259.egg-info/top_level.txt