Metadata-Version: 2.1
Name: Topsis-Kamal-102103259
Version: 1.0.14
Summary: A python package for implementing topsis
Home-page: https://github.com/kkamal2003/Topsis_Kamal_102103259
Author: Kamalpreet Kaur
Author-email: kkamal101203@gmail.com
License: UNKNOWN
Platform: UNKNOWN
Classifier: Programming Language :: Python :: 3
Classifier: License :: OSI Approved :: MIT License
Classifier: Operating System :: OS Independent
